{"PubmedBookArticle": [], "PubmedArticle": [{"MedlineCitation": {"OtherID": [], "KeywordList": [], "OtherAbstract": [], "CitationSubset": ["IM"], "SpaceFlightMission": [], "GeneralNote": [], "PMID": "33122688", "DateCompleted": {"Year": "2020", "Month": "11", "Day": "12"}, "DateRevised": {"Year": "2020", "Month": "11", "Day": "12"}, "Article": {"ELocationID": ["10.1038/s41598-020-75554-z"], "ArticleDate": [{"Year": "2020", "Month": "10", "Day": "29"}], "Language": ["eng"], "Journal": {"ISSN": "2045-2322", "JournalIssue": {"Volume": "10", "Issue": "1", "PubDate": {"Year": "2020", "Month": "10", "Day": "29"}}, "Title": "Scientific reports", "ISOAbbreviation": "Sci Rep"}, "ArticleTitle": "Simultaneous analysis of five triterpenes in Centella asiatica by high performance liquid chromatography with cyclodextrins as the mobile phase additives.", "Pagination": {"MedlinePgn": "18577"}, "Abstract": {"AbstractText": ["Triterpenes are considered the major active components in Centella asiatica (L.) Urb. (C. asiatica), such as asiatic acid, madecassic acid, asiaticoside, madecassoside and asiaticoside B. It is difficult to simultaneously determine five triterpenes because of madecassoside isomers (madecassoside and asiaticoside B), and the great polarity difference between triterpene acid and triterpene glycoside. In this study, a simple high performance liquid chromatography method with isocratic elution employing cyclodextrins (CDs) as the mobile phase additives was developed to determine five triterpenes in C. asiatica. Various factors affecting triterpenes retention in the C18 column, such as the nature of CDs, \u03b3-CD concentration, acetonitrile percentage and temperature, were studied. Experimental results showed that \u03b3-CD, as an effective mobile phase additive, could markedly reduce the retention of triterpenes (especially asiatic acid and madecassic acid), and improve the separation for madecassoside and asiaticoside B. The elution of five triterpenes could be achieved on an ODS C18 column within 30\u00a0min using the acetonitrile-0.2% phosphoric acid contained 4.0\u00a0mM \u03b3-CD (20:80, v/v) mixture as the mobile phase. The retention modification of triterpenes may be attributed to the formation of the triterpenes-\u03b3-CD inclusion complexes. The optimized method was successfully applied for simultaneous determination of five triterpenes in C. asiatica."]}, "AuthorList": [{"Identifier": [], "AffiliationInfo": [{"Identifier": [], "Affiliation": "Shaanxi Institute for Food and Drug Control, No 21, Keji Fifth Road, Xi'an, 710065, Shaanxi Province, China."}], "LastName": "Wang", "ForeName": "Changhe", "Initials": "C"}, {"Identifier": [], "AffiliationInfo": [{"Identifier": [], "Affiliation": "Nanjing Aureole Pharmaceutical Co., Ltd., No.11, Changchun Road, High Tech Zone, Zhengzhou, 450001, Henan Province, China."}], "LastName": "Zhao", "ForeName": "Yanan", "Initials": "Y"}, {"Identifier": [], "AffiliationInfo": [{"Identifier": [], "Affiliation": "Xi'an University, No 1, Keji Sixth Road, Xi'an, 710065, Shaanxi Province, China."}], "LastName": "Yang", "ForeName": "Ruomeng", "Initials": "R"}, {"Identifier": [], "AffiliationInfo": [{"Identifier": [], "Affiliation": "Shaanxi Institute for Food and Drug Control, No 21, Keji Fifth Road, Xi'an, 710065, Shaanxi Province, China. 99159512@qq.com."}], "LastName": "Liu", "ForeName": "Haijing", "Initials": "H"}], "PublicationTypeList": ["Journal Article"]}, "MedlineJournalInfo": {"Country": "England", "MedlineTA": "Sci Rep", "NlmUniqueID": "101563288", "ISSNLinking": "2045-2322"}}, "PubmedData": {"ReferenceList": [{"ReferenceList": [], "Reference": [{"Citation": "Int J Pharm. 2015 Jul 25;490(1-2):240-7", "ArticleIdList": ["26024819"]}, {"Citation": "Sci Rep. 2019 Jun 10;9(1):8404", "ArticleIdList": ["31182820"]}, {"Citation": "BMC Complement Altern Med. 2019 Aug 14;19(1):213", "ArticleIdList": ["31412845"]}, {"Citation": "J Sci Food Agric. 2011 Dec;91(15):2731-9", "ArticleIdList": ["21987075"]}, {"Citation": "Anal Bioanal Chem. 2012 Mar;402(9):2935-43", "ArticleIdList": ["22349325"]}, {"Citation": "J Chromatogr B Analyt Technol Biomed Life Sci. 2009 Aug 1;877(23):2396-402", "ArticleIdList": ["19349219"]}, {"Citation": "J Ethnopharmacol. 2012 Mar 27;140(2):333-8", "ArticleIdList": ["22301444"]}, {"Citation": "J Ethnopharmacol. 1995 Aug 11;48(1):53-7", "ArticleIdList": ["8569247"]}, {"Citation": "J Sep Sci. 2011 Nov;34(21):3023-8", "ArticleIdList": ["21994210"]}, {"Citation": "J Pharm Bioallied Sci. 2014 Apr;6(2):86-91", "ArticleIdList": ["24741275"]}, {"Citation": "Planta Med. 1994 Apr;60(2):133-5", "ArticleIdList": ["8202564"]}, {"Citation": "Biomed Chromatogr. 2010 Aug;24(8):799-807", "ArticleIdList": ["20017213"]}, {"Citation": "Planta Med. 2019 Nov;85(16):1203-1215", "ArticleIdList": ["31539918"]}, {"Citation": "Pharm Biol. 2012 Dec;50(12):1508-12", "ArticleIdList": ["22966846"]}, {"Citation": "Anal Chim Acta. 2012 Jan 27;712:145-51", "ArticleIdList": ["22177078"]}, {"Citation": "J Sep Sci. 2012 Dec;35(24):3469-76", "ArticleIdList": ["23165721"]}, {"Citation": "Neurosci Lett. 2017 Apr 12;646:24-29", "ArticleIdList": ["28279707"]}, {"Citation": "BMC Complement Altern Med. 2012 Jul 20;12:103", "ArticleIdList": ["22817824"]}, {"Citation": "Evid Based Complement Alternat Med. 2012;2012:848093", "ArticleIdList": ["23346217"]}]}], "History": [{"Year": "2020", "Month": "03", "Day": "04"}, {"Year": "2020", "Month": "10", "Day": "14"}, {"Year": "2020", "Month": "10", "Day": "30", "Hour": "5", "Minute": "48"}, {"Year": "2020", "Month": "10", "Day": "31", "Hour": "6", "Minute": "0"}, {"Year": "2020", "Month": "10", "Day": "31", "Hour": "6", "Minute": "1"}], "PublicationStatus": "epublish", "ArticleIdList": ["33122688", "10.1038/s41598-020-75554-z", "10.1038/s41598-020-75554-z", "PMC7596059"]}}]}