{"PubmedBookArticle": [], "PubmedArticle": [{"MedlineCitation": {"OtherID": [], "KeywordList": [], "OtherAbstract": [], "CitationSubset": ["IM"], "SpaceFlightMission": [], "GeneralNote": [], "PMID": "4961798", "DateCompleted": {"Year": "1967", "Month": "09", "Day": "24"}, "DateRevised": {"Year": "2019", "Month": "10", "Day": "21"}, "Article": {"ELocationID": [], "ArticleDate": [], "Language": ["fre"], "Journal": {"JournalIssue": {"Volume": "264", "Issue": "2", "PubDate": {"Year": "1967", "Month": "Jan", "Day": "09"}}, "Title": "Comptes rendus hebdomadaires des seances de l'Academie des sciences. Serie D: Sciences naturelles", "ISOAbbreviation": "C R Acad Hebd Seances Acad Sci D"}, "ArticleTitle": "[Isolation of a new triterpenic acid from Centella asiatica (L.) Urb. of Madagascar: madecassic acid].", "Pagination": {"MedlinePgn": "407-10"}, "AuthorList": [{"Identifier": [], "AffiliationInfo": [], "LastName": "Boiteau", "ForeName": "P", "Initials": "P"}, {"Identifier": [], "AffiliationInfo": [], "LastName": "Chanez", "ForeName": "M", "Initials": "M"}], "PublicationTypeList": ["Journal Article"], "VernacularTitle": "Isolement d'un nouvel acide triterp\u00e9nique de Centella asiatica (L.) Urb. de Madagascar: l'acide mad\u00e9cassique."}, "MedlineJournalInfo": {"Country": "France", "MedlineTA": "C R Acad Hebd Seances Acad Sci D", "NlmUniqueID": "7501107"}, "ChemicalList": [{"RegistryNumber": "0", "NameOfSubstance": "Terpenes"}], "MeshHeadingList": [{"QualifierName": [], "DescriptorName": "Plants, Medicinal"}, {"QualifierName": [], "DescriptorName": "Terpenes"}]}, "PubmedData": {"ReferenceList": [], "History": [{"Year": "1967", "Month": "1", "Day": "9"}, {"Year": "1967", "Month": "1", "Day": "9", "Hour": "0", "Minute": "1"}, {"Year": "1967", "Month": "1", "Day": "9", "Hour": "0", "Minute": "0"}], "PublicationStatus": "ppublish", "ArticleIdList": ["4961798"]}}]}